html_snapshot.py
html_snapshot-0.1.2.dist-info/licenses/LICENSE
html_snapshot-0.1.2.dist-info/METADATA
html_snapshot-0.1.2.dist-info/WHEEL
html_snapshot-0.1.2.dist-info/entry_points.txt
html_snapshot-0.1.2.dist-info/top_level.txt
html_snapshot-0.1.2.dist-info/RECORD
