Metadata-Version: 2.4
Name: html-snapshot
Version: 0.1.2
Summary: Capture a PNG screenshot of a local HTML presentation using Playwright
Author: Mehmet Oner Yalcin
License-Expression: MIT
Project-URL: Homepage, https://github.com/oneryalcin/html-snapshot
Project-URL: Source, https://github.com/oneryalcin/html-snapshot
Project-URL: Issues, https://github.com/oneryalcin/html-snapshot/issues
Requires-Python: >=3.10
License-File: LICENSE
Requires-Dist: playwright>=1.46
Dynamic: license-file
